[{"mp": "39:38", "fg": "11", "fga": "20", "fg3": "3", "ft": "5", "fta": "5", "trb": "8", "ast": "5", "stl": "5", "blk": "1", "pts": "30", "game_score": "31.0"}, {"mp": "46:25", "fg": "11", "fga": "19", "fg3": "1", "ft": "9", "fta": "9", "trb": "9", "ast": "3", "stl": "2", "blk": "1", "pts": "32", "game_score": "28.2"}, {"mp": "45:30", "fg": "14", "fga": "23", "fg3": "4", "ft": "3", "fta": "4", "trb": "7", "ast": "3", "stl": "2", "blk": "0", "pts": "35", "game_score": "26.5"}, {"mp": "42:20", "fg": "8", "fga": "14", "fg3": "3", "ft": "9", "fta": "10", "trb": "9", "ast": "4", "stl": "4", "blk": "0", "pts": "28", "game_score": "26.3"}, {"mp": "32:16", "fg": "12", "fga": "18", "fg3": "3", "ft": "3", "fta": "3", "trb": "4", "ast": "3", "stl": "1", "blk": "1", "pts": "30", "game_score": "24.8"}, {"mp": "43:08", "fg": "9", "fga": "13", "fg3": "2", "ft": "9", "fta": "9", "trb": "4", "ast": "2", "stl": "1", "blk": "1", "pts": "29", "game_score": "22.6"}, {"mp": "45:13", "fg": "8", "fga": "20", "fg3": "1", "ft": "9", "fta": "11", "trb": "11", "ast": "4", "stl": "3", "blk": "2", "pts": "26", "game_score": "22.5"}, {"mp": "35:42", "fg": "10", "fga": "19", "fg3": "2", "ft": "5", "fta": "6", "trb": "5", "ast": "2", "stl": "3", "blk": "0", "pts": "27", "game_score": "22.2"}, {"mp": "43:34", "fg": "12", "fga": "18", "fg3": "0", "ft": "3", "fta": "4", "trb": "5", "ast": "4", "stl": "1", "blk": "1", "pts": "27", "game_score": "21.6"}, {"mp": "36:46", "fg": "8", "fga": "15", "fg3": "1", "ft": "6", "fta": "6", "trb": "6", "ast": "5", "stl": "0", "blk": "2", "pts": "23", "game_score": "21.4"}, {"mp": "38:48", "fg": "9", "fga": "17", "fg3": "2", "ft": "5", "fta": "6", "trb": "3", "ast": "2", "stl": "2", "blk": "2", "pts": "25", "game_score": "21.0"}, {"mp": "43:27", "fg": "11", "fga": "22", "fg3": "2", "ft": "1", "fta": "1", "trb": "6", "ast": "5", "stl": "4", "blk": "0", "pts": "25", "game_score": "20.9"}, {"mp": "40:08", "fg": "8", "fga": "17", "fg3": "2", "ft": "6", "fta": "9", "trb": "4", "ast": "3", "stl": "2", "blk": "5", "pts": "24", "game_score": "20.7"}, {"mp": "45:03", "fg": "8", "fga": "12", "fg3": "1", "ft": "3", "fta": "3", "trb": "8", "ast": "5", "stl": "2", "blk": "0", "pts": "20", "game_score": "20.5"}, {"mp": "46:01", "fg": "10", "fga": "13", "fg3": "0", "ft": "6", "fta": "9", "trb": "3", "ast": "2", "stl": "1", "blk": "1", "pts": "26", "game_score": "20.3"}, {"mp": "38:54", "fg": "8", "fga": "14", "fg3": "1", "ft": "5", "fta": "6", "trb": "7", "ast": "7", "stl": "2", "blk": "1", "pts": "22", "game_score": "20.3"}, {"mp": "48:25", "fg": "7", "fga": "12", "fg3": "1", "ft": "7", "fta": "8", "trb": "4", "ast": "3", "stl": "1", "blk": "2", "pts": "22", "game_score": "19.3"}, {"mp": "43:55", "fg": "9", "fga": "19", "fg3": "0", "ft": "3", "fta": "4", "trb": "8", "ast": "3", "stl": "3", "blk": "1", "pts": "21", "game_score": "18.9"}, {"mp": "39:17", "fg": "9", "fga": "17", "fg3": "0", "ft": "4", "fta": "4", "trb": "4", "ast": "5", "stl": "2", "blk": "1", "pts": "22", "game_score": "17.9"}, {"mp": "48:57", "fg": "10", "fga": "18", "fg3": "0", "ft": "2", "fta": "2", "trb": "6", "ast": "4", "stl": "1", "blk": "2", "pts": "22", "game_score": "17.6"}, {"mp": "39:14", "fg": "9", "fga": "15", "fg3": "1", "ft": "4", "fta": "4", "trb": "5", "ast": "4", "stl": "2", "blk": "0", "pts": "23", "game_score": "17.2"}, {"mp": "30:41", "fg": "7", "fga": "16", "fg3": "1", "ft": "6", "fta": "7", "trb": "10", "ast": "2", "stl": "1", "blk": "0", "pts": "21", "game_score": "16.8"}, {"mp": "28:43", "fg": "8", "fga": "14", "fg3": "0", "ft": "3", "fta": "4", "trb": "4", "ast": "3", "stl": "4", "blk": "1", "pts": "19", "game_score": "15.8"}, {"mp": "40:15", "fg": "6", "fga": "13", "fg3": "1", "ft": "5", "fta": "6", "trb": "5", "ast": "6", "stl": "5", "blk": "1", "pts": "18", "game_score": "15.3"}, {"mp": "37:10", "fg": "9", "fga": "18", "fg3": "0", "ft": "2", "fta": "4", "trb": "5", "ast": "3", "stl": "3", "blk": "1", "pts": "20", "game_score": "15.3"}, {"mp": "41:24", "fg": "10", "fga": "18", "fg3": "1", "ft": "1", "fta": "2", "trb": "6", "ast": "3", "stl": "1", "blk": "1", "pts": "22", "game_score": "15.2"}, {"mp": "39:24", "fg": "8", "fga": "20", "fg3": "2", "ft": "3", "fta": "4", "trb": "7", "ast": "2", "stl": "1", "blk": "1", "pts": "21", "game_score": "15.0"}, {"mp": "49:33", "fg": "8", "fga": "23", "fg3": "2", "ft": "4", "fta": "6", "trb": "8", "ast": "5", "stl": "1", "blk": "1", "pts": "22", "game_score": "14.9"}, {"mp": "40:05", "fg": "7", "fga": "15", "fg3": "0", "ft": "2", "fta": "2", "trb": "5", "ast": "4", "stl": "2", "blk": "2", "pts": "16", "game_score": "14.4"}, {"mp": "40:28", "fg": "7", "fga": "15", "fg3": "1", "ft": "3", "fta": "4", "trb": "8", "ast": "3", "stl": "1", "blk": "1", "pts": "18", "game_score": "14.1"}, {"mp": "38:14", "fg": "8", "fga": "18", "fg3": "2", "ft": "4", "fta": "4", "trb": "8", "ast": "3", "stl": "0", "blk": "0", "pts": "22", "game_score": "13.9"}, {"mp": "36:55", "fg": "7", "fga": "14", "fg3": "1", "ft": "2", "fta": "3", "trb": "5", "ast": "6", "stl": "2", "blk": "0", "pts": "17", "game_score": "13.9"}]